vertica_mcp/__init__.py
vertica_mcp/cli.py
vertica_mcp/connection.py
vertica_mcp/py.typed
vertica_mcp/server.py
vertica_mcp/utils.py
vertica_mcp-0.1.3.dist-info/licenses/LICENSE
vertica_mcp-0.1.3.dist-info/METADATA
vertica_mcp-0.1.3.dist-info/WHEEL
vertica_mcp-0.1.3.dist-info/entry_points.txt
vertica_mcp-0.1.3.dist-info/top_level.txt
vertica_mcp-0.1.3.dist-info/RECORD
