Metadata-Version: 2.4
Name: vertica-mcp
Version: 0.1.3
Summary: Production-ready MCP server for Vertica—secure tools, row streaming, pagination, and system metrics for LLM agents (Claude, Cursor, VS Code).
Author-email: Abdelhak Zabour <abdelhakzabour@gmail.com>
Maintainer: Abdelhak Zabour
License-Expression: Apache-2.0
Project-URL: Homepage, https://github.com/zaboura/vertica-mcp
Project-URL: Repository, https://github.com/zaboura/vertica-mcp
Project-URL: Documentation, https://github.com/zaboura/vertica-mcp#readme
Project-URL: Issues, https://github.com/zaboura/vertica-mcp/issues
Project-URL: Changelog, https://github.com/zaboura/vertica-mcp/blob/master/CHANGELOG.md
Keywords: vertica,database,mcp,model-context-protocol,llm,agent,ai,data,analytics,cli,claude,cursor,anthropic,data-science
Requires-Python: >=3.11
License-File: LICENSE
Requires-Dist: click>=8.1.0
Requires-Dist: mcp[cli]>=1.8.0
Requires-Dist: python-dotenv>=1.1.1
Requires-Dist: vertica-python>=1.4.0
Requires-Dist: starlette>=0.46
Requires-Dist: uvicorn>=0.34
Requires-Dist: fastmcp>=2.11.3
Provides-Extra: dev
Requires-Dist: black>=23.0.0; extra == "dev"
Requires-Dist: isort>=5.12.0; extra == "dev"
Requires-Dist: mypy>=1.5.0; extra == "dev"
Requires-Dist: ruff>=0.1.0; extra == "dev"
Requires-Dist: pytest>=7.4.0; extra == "dev"
Requires-Dist: pytest-asyncio>=0.23; extra == "dev"
Requires-Dist: pytest-cov>=5.0; extra == "dev"
Requires-Dist: pytest-mock>=3.11.0; extra == "dev"
Requires-Dist: requests>=2.32; extra == "dev"
Requires-Dist: build>=1.0.0; extra == "dev"
Requires-Dist: twine>=4.0.0; extra == "dev"
Provides-Extra: test
Requires-Dist: pytest>=7.4.0; extra == "test"
Requires-Dist: pytest-asyncio>=0.23; extra == "test"
Requires-Dist: pytest-cov>=5.0; extra == "test"
Requires-Dist: pytest-mock>=3.11.0; extra == "test"
Requires-Dist: requests>=2.32; extra == "test"
Provides-Extra: docs
Requires-Dist: mkdocs>=1.5.0; extra == "docs"
Requires-Dist: mkdocs-material>=9.0.0; extra == "docs"
Requires-Dist: mkdocstrings[python]>=0.22.0; extra == "docs"
Provides-Extra: perf
Requires-Dist: pytest-benchmark>=4.0.0; extra == "perf"
Requires-Dist: memory-profiler>=0.61.0; extra == "perf"
Dynamic: license-file
